MANIFEST.in
README
README.rst
setup.cfg
setup.py
PyBabel_json_md.egg-info/PKG-INFO
PyBabel_json_md.egg-info/SOURCES.txt
PyBabel_json_md.egg-info/dependency_links.txt
PyBabel_json_md.egg-info/entry_points.txt
PyBabel_json_md.egg-info/pbr.json
PyBabel_json_md.egg-info/requires.txt
PyBabel_json_md.egg-info/top_level.txt
pybabel_json_md/__init__.py
pybabel_json_md/extractor.py
test/test.json