Metadata-Version: 1.1
Name: PyBabel-json-md
Version: 0.1.0
Summary: PyBabel json metadef (md) gettext strings extractor
Home-page: https://github.com/wkoathp/pybabel-json-md
Author: Wayne Okuma
Author-email: wayne.okuma@hpe.com
License: UNKNOWN
Platform: UNKNOWN
Classifier: Development Status :: 5 - Production/Stable
Classifier: Intended Audience :: Developers
Classifier: License :: OSI Approved :: Apache Software License
Classifier: Operating System :: OS Independent
Classifier: Programming Language :: Python
Classifier: Programming Language :: Python :: 2.6
Classifier: Programming Language :: Python :: 2.7
Classifier: Programming Language :: Python :: 3
Classifier: Programming Language :: Python :: 3.4
Classifier: Topic :: Software Development :: Libraries :: Python Modules
